rtl/core/pc.v
//Program counter
`timescale 1ns/1ps

module pc (
    input i_Clock,
    input i_Reset,

    input i_Branch,
    input i_Zero,
    input [63:0] i_Immediate,

    output reg [63:0] o_PC
);

always @(posedge i_Clock) begin
    if(i_Reset == 1'b1) begin
        o_PC <= 64'b0;
    end else begin
        //PC + 4 || PC + Imm when branch
        o_PC <= (i_Branch & i_Zero) ? (o_PC + i_Immediate) : (o_PC + 4);
    end
end
endmodule

sim/pc_tb.v
`timescale 1ns/10ps
 
`include "../rtl/core/pc.v"
 
module pc_tb ();
parameter c_CLOCK_PERIOD_NS = 100;
reg r_Clock = 0;
reg r_Reset = 1;

reg r_Branch, r_Zero;
reg [63:0] r_Immediate;
wire [63:0] w_PC;
   
   
pc dut(
    .i_Clock(r_Clock),
    .i_Reset(r_Reset),
    .i_Branch(r_Branch),
    .i_Zero(r_Zero),
    .i_Immediate(r_Immediate),
    .o_PC(w_PC)
);
 
always #(c_CLOCK_PERIOD_NS/2) r_Clock <= !r_Clock;
   
// Main Testing:
initial begin
    $dumpfile("../runs/pc_tb.vcd");
    $dumpvars(0,r_Clock,r_Reset, r_Branch, r_Zero, r_Immediate, w_PC);
    $display("Begin simulation");
    @(posedge r_Clock);
    r_Reset <= 0; r_Branch <= 0; r_Zero <= 0; r_Immediate <= 0;
end

initial begin
    #200000;
    $finish;
end

endmodule

runs/pc_tb.vcd
$date
	Sat Jul 16 22:35:43 2022
$end
$version
	Icarus Verilog
$end
$timescale
	1ps
$end
$scope module pc_tb $end
$var reg 1 ! r_Clock $end
$upscope $end
$scope module pc_tb $end
$var reg 1 " r_Reset $end
$upscope $end
$scope module pc_tb $end
$var reg 1 # r_Branch $end
$upscope $end
$scope module pc_tb $end
$var reg 1 $ r_Zero $end
$upscope $end
$scope module pc_tb $end
$var reg 64 % r_Immediate [63:0] $end
$upscope $end
$scope module pc_tb $end
$var wire 64 & w_PC [63:0] $end
$upscope $end
$enddefinitions $end
#0
$dumpvars
bx &
bx %
x$
x#
1"
0!
$end
#50000
b0 &
b0 %
0$
0#
0"
1!
#100000
0!
#150000
b100 &
1!
#200000
0!
#250000
b1000 &
1!
#300000
0!
#350000
b1100 &
1!
#400000
0!
#450000
b10000 &
1!
#500000
0!
#550000
b10100 &
1!
#600000
0!
#650000
b11000 &
1!
#700000
0!
#750000
b11100 &
1!
#800000
0!
#850000
b100000 &
1!
#900000
0!
#950000
b100100 &
1!
#1000000
0!
#1050000
b101000 &
1!
#1100000
0!
#1150000
b101100 &
1!
#1200000
0!
#1250000
b110000 &
1!
#1300000
0!
#1350000
b110100 &
1!
#1400000
0!
#1450000
b111000 &
1!
#1500000
0!
#1550000
b111100 &
1!
#1600000
0!
#1650000
b1000000 &
1!
#1700000
0!
#1750000
b1000100 &
1!
#1800000
0!
#1850000
b1001000 &
1!
#1900000
0!
#1950000
b1001100 &
1!
#2000000
0!
#2050000
b1010000 &
1!
#2100000
0!
#2150000
b1010100 &
1!
#2200000
0!
#2250000
b1011000 &
1!
#2300000
0!
#2350000
b1011100 &
1!
#2400000
0!
#2450000
b1100000 &
1!
#2500000
0!
#2550000
b1100100 &
1!
#2600000
0!
#2650000
b1101000 &
1!
#2700000
0!
#2750000
b1101100 &
1!
#2800000
0!
#2850000
b1110000 &
1!
#2900000
0!
#2950000
b1110100 &
1!
#3000000
0!
#3050000
b1111000 &
1!
#3100000
0!
#3150000
b1111100 &
1!
#3200000
0!
#3250000
b10000000 &
1!
#3300000
0!
#3350000
b10000100 &
1!
#3400000
0!
#3450000
b10001000 &
1!
#3500000
0!
#3550000
b10001100 &
1!
#3600000
0!
#3650000
b10010000 &
1!
#3700000
0!
#3750000
b10010100 &
1!
#3800000
0!
#3850000
b10011000 &
1!
#3900000
0!
#3950000
b10011100 &
1!
#4000000
0!
#4050000
b10100000 &
1!
#4100000
0!
#4150000
b10100100 &
1!
#4200000
0!
#4250000
b10101000 &
1!
#4300000
0!
#4350000
b10101100 &
1!
#4400000
0!
#4450000
b10110000 &
1!
#4500000
0!
#4550000
b10110100 &
1!
#4600000
0!
#4650000
b10111000 &
1!
#4700000
0!
#4750000
b10111100 &
1!
#4800000
0!
#4850000
b11000000 &
1!
#4900000
0!
#4950000
b11000100 &
1!
#5000000
0!
#5050000
b11001000 &
1!
#5100000
0!
#5150000
b11001100 &
1!
#5200000
0!
#5250000
b11010000 &
1!
#5300000
0!
#5350000
b11010100 &
1!
#5400000
0!
#5450000
b11011000 &
1!
#5500000
0!
#5550000
b11011100 &
1!
#5600000
0!
#5650000
b11100000 &
1!
#5700000
0!
#5750000
b11100100 &
1!
#5800000
0!
#5850000
b11101000 &
1!
#5900000
0!
#5950000
b11101100 &
1!
#6000000
0!
#6050000
b11110000 &
1!
#6100000
0!
#6150000
b11110100 &
1!
#6200000
0!
#6250000
b11111000 &
1!
#6300000
0!
#6350000
b11111100 &
1!
#6400000
0!
#6450000
b100000000 &
1!
#6500000
0!
#6550000
b100000100 &
1!
#6600000
0!
#6650000
b100001000 &
1!
#6700000
0!
#6750000
b100001100 &
1!
#6800000
0!
#6850000
b100010000 &
1!
#6900000
0!
#6950000
b100010100 &
1!
#7000000
0!
#7050000
b100011000 &
1!
#7100000
0!
#7150000
b100011100 &
1!
#7200000
0!
#7250000
b100100000 &
1!
#7300000
0!
#7350000
b100100100 &
1!
#7400000
0!
#7450000
b100101000 &
1!
#7500000
0!
#7550000
b100101100 &
1!
#7600000
0!
#7650000
b100110000 &
1!
#7700000
0!
#7750000
b100110100 &
1!
#7800000
0!
#7850000
b100111000 &
1!
#7900000
0!
#7950000
b100111100 &
1!
#8000000
0!
#8050000
b101000000 &
1!
#8100000
0!
#8150000
b101000100 &
1!
#8200000
0!
#8250000
b101001000 &
1!
#8300000
0!
#8350000
b101001100 &
1!
#8400000
0!
#8450000
b101010000 &
1!
#8500000
0!
#8550000
b101010100 &
1!
#8600000
0!
#8650000
b101011000 &
1!
#8700000
0!
#8750000
b101011100 &
1!
#8800000
0!
#8850000
b101100000 &
1!
#8900000
0!
#8950000
b101100100 &
1!
#9000000
0!
#9050000
b101101000 &
1!
#9100000
0!
#9150000
b101101100 &
1!
#9200000
0!
#9250000
b101110000 &
1!
#9300000
0!
#9350000
b101110100 &
1!
#9400000
0!
#9450000
b101111000 &
1!
#9500000
0!
#9550000
b101111100 &
1!
#9600000
0!
#9650000
b110000000 &
1!
#9700000
0!
#9750000
b110000100 &
1!
#9800000
0!
#9850000
b110001000 &
1!
#9900000
0!
#9950000
b110001100 &
1!
#10000000
0!
#10050000
b110010000 &
1!
#10100000
0!
#10150000
b110010100 &
1!
#10200000
0!
#10250000
b110011000 &
1!
#10300000
0!
#10350000
b110011100 &
1!
#10400000
0!
#10450000
b110100000 &
1!
#10500000
0!
#10550000
b110100100 &
1!
#10600000
0!
#10650000
b110101000 &
1!
#10700000
0!
#10750000
b110101100 &
1!
#10800000
0!
#10850000
b110110000 &
1!
#10900000
0!
#10950000
b110110100 &
1!
#11000000
0!
#11050000
b110111000 &
1!
#11100000
0!
#11150000
b110111100 &
1!
#11200000
0!
#11250000
b111000000 &
1!
#11300000
0!
#11350000
b111000100 &
1!
#11400000
0!
#11450000
b111001000 &
1!
#11500000
0!
#11550000
b111001100 &
1!
#11600000
0!
#11650000
b111010000 &
1!
#11700000
0!
#11750000
b111010100 &
1!
#11800000
0!
#11850000
b111011000 &
1!
#11900000
0!
#11950000
b111011100 &
1!
#12000000
0!
#12050000
b111100000 &
1!
#12100000
0!
#12150000
b111100100 &
1!
#12200000
0!
#12250000
b111101000 &
1!
#12300000
0!
#12350000
b111101100 &
1!
#12400000
0!
#12450000
b111110000 &
1!
#12500000
0!
#12550000
b111110100 &
1!
#12600000
0!
#12650000
b111111000 &
1!
#12700000
0!
#12750000
b111111100 &
1!
#12800000
0!
#12850000
b1000000000 &
1!
#12900000
0!
#12950000
b1000000100 &
1!
#13000000
0!
#13050000
b1000001000 &
1!
#13100000
0!
#13150000
b1000001100 &
1!
#13200000
0!
#13250000
b1000010000 &
1!
#13300000
0!
#13350000
b1000010100 &
1!
#13400000
0!
#13450000
b1000011000 &
1!
#13500000
0!
#13550000
b1000011100 &
1!
#13600000
0!
#13650000
b1000100000 &
1!
#13700000
0!
#13750000
b1000100100 &
1!
#13800000
0!
#13850000
b1000101000 &
1!
#13900000
0!
#13950000
b1000101100 &
1!
#14000000
0!
#14050000
b1000110000 &
1!
#14100000
0!
#14150000
b1000110100 &
1!
#14200000
0!
#14250000
b1000111000 &
1!
#14300000
0!
#14350000
b1000111100 &
1!
#14400000
0!
#14450000
b1001000000 &
1!
#14500000
0!
#14550000
b1001000100 &
1!
#14600000
0!
#14650000
b1001001000 &
1!
#14700000
0!
#14750000
b1001001100 &
1!
#14800000
0!
#14850000
b1001010000 &
1!
#14900000
0!
#14950000
b1001010100 &
1!
#15000000
0!
#15050000
b1001011000 &
1!
#15100000
0!
#15150000
b1001011100 &
1!
#15200000
0!
#15250000
b1001100000 &
1!
#15300000
0!
#15350000
b1001100100 &
1!
#15400000
0!
#15450000
b1001101000 &
1!
#15500000
0!
#15550000
b1001101100 &
1!
#15600000
0!
#15650000
b1001110000 &
1!
#15700000
0!
#15750000
b1001110100 &
1!
#15800000
0!
#15850000
b1001111000 &
1!
#15900000
0!
#15950000
b1001111100 &
1!
#16000000
0!
#16050000
b1010000000 &
1!
#16100000
0!
#16150000
b1010000100 &
1!
#16200000
0!
#16250000
b1010001000 &
1!
#16300000
0!
#16350000
b1010001100 &
1!
#16400000
0!
#16450000
b1010010000 &
1!
#16500000
0!
#16550000
b1010010100 &
1!
#16600000
0!
#16650000
b1010011000 &
1!
#16700000
0!
#16750000
b1010011100 &
1!
#16800000
0!
#16850000
b1010100000 &
1!
#16900000
0!
#16950000
b1010100100 &
1!
#17000000
0!
#17050000
b1010101000 &
1!
#17100000
0!
#17150000
b1010101100 &
1!
#17200000
0!
#17250000
b1010110000 &
1!
#17300000
0!
#17350000
b1010110100 &
1!
#17400000
0!
#17450000
b1010111000 &
1!
#17500000
0!
#17550000
b1010111100 &
1!
#17600000
0!
#17650000
b1011000000 &
1!
#17700000
0!
#17750000
b1011000100 &
1!
#17800000
0!
#17850000
b1011001000 &
1!
#17900000
0!
#17950000
b1011001100 &
1!
#18000000
0!
#18050000
b1011010000 &
1!
#18100000
0!
#18150000
b1011010100 &
1!
#18200000
0!
#18250000
b1011011000 &
1!
#18300000
0!
#18350000
b1011011100 &
1!
#18400000
0!
#18450000
b1011100000 &
1!
#18500000
0!
#18550000
b1011100100 &
1!
#18600000
0!
#18650000
b1011101000 &
1!
#18700000
0!
#18750000
b1011101100 &
1!
#18800000
0!
#18850000
b1011110000 &
1!
#18900000
0!
#18950000
b1011110100 &
1!
#19000000
0!
#19050000
b1011111000 &
1!
#19100000
0!
#19150000
b1011111100 &
1!
#19200000
0!
#19250000
b1100000000 &
1!
#19300000
0!
#19350000
b1100000100 &
1!
#19400000
0!
#19450000
b1100001000 &
1!
#19500000
0!
#19550000
b1100001100 &
1!
#19600000
0!
#19650000
b1100010000 &
1!
#19700000
0!
#19750000
b1100010100 &
1!
#19800000
0!
#19850000
b1100011000 &
1!
#19900000
0!
#19950000
b1100011100 &
1!
#20000000
0!
#20050000
b1100100000 &
1!
#20100000
0!
#20150000
b1100100100 &
1!
#20200000
0!
#20250000
b1100101000 &
1!
#20300000
0!
#20350000
b1100101100 &
1!
#20400000
0!
#20450000
b1100110000 &
1!
#20500000
0!
#20550000
b1100110100 &
1!
#20600000
0!
#20650000
b1100111000 &
1!
#20700000
0!
#20750000
b1100111100 &
1!
#20800000
0!
#20850000
b1101000000 &
1!
#20900000
0!
#20950000
b1101000100 &
1!
#21000000
0!
#21050000
b1101001000 &
1!
#21100000
0!
#21150000
b1101001100 &
1!
#21200000
0!
#21250000
b1101010000 &
1!
#21300000
0!
#21350000
b1101010100 &
1!
#21400000
0!
#21450000
b1101011000 &
1!
#21500000
0!
#21550000
b1101011100 &
1!
#21600000
0!
#21650000
b1101100000 &
1!
#21700000
0!
#21750000
b1101100100 &
1!
#21800000
0!
#21850000
b1101101000 &
1!
#21900000
0!
#21950000
b1101101100 &
1!
#22000000
0!
#22050000
b1101110000 &
1!
#22100000
0!
#22150000
b1101110100 &
1!
#22200000
0!
#22250000
b1101111000 &
1!
#22300000
0!
#22350000
b1101111100 &
1!
#22400000
0!
#22450000
b1110000000 &
1!
#22500000
0!
#22550000
b1110000100 &
1!
#22600000
0!
#22650000
b1110001000 &
1!
#22700000
0!
#22750000
b1110001100 &
1!
#22800000
0!
#22850000
b1110010000 &
1!
#22900000
0!
#22950000
b1110010100 &
1!
#23000000
0!
#23050000
b1110011000 &
1!
#23100000
0!
#23150000
b1110011100 &
1!
#23200000
0!
#23250000
b1110100000 &
1!
#23300000
0!
#23350000
b1110100100 &
1!
#23400000
0!
#23450000
b1110101000 &
1!
#23500000
0!
#23550000
b1110101100 &
1!
#23600000
0!
#23650000
b1110110000 &
1!
#23700000
0!
#23750000
b1110110100 &
1!
#23800000
0!
#23850000
b1110111000 &
1!
#23900000
0!
#23950000
b1110111100 &
1!
#24000000
0!
#24050000
b1111000000 &
1!
#24100000
0!
#24150000
b1111000100 &
1!
#24200000
0!
#24250000
b1111001000 &
1!
#24300000
0!
#24350000
b1111001100 &
1!
#24400000
0!
#24450000
b1111010000 &
1!
#24500000
0!
#24550000
b1111010100 &
1!
#24600000
0!
#24650000
b1111011000 &
1!
#24700000
0!
#24750000
b1111011100 &
1!
#24800000
0!
#24850000
b1111100000 &
1!
#24900000
0!
#24950000
b1111100100 &
1!
#25000000
0!
#25050000
b1111101000 &
1!
#25100000
0!
#25150000
b1111101100 &
1!
#25200000
0!
#25250000
b1111110000 &
1!
#25300000
0!
#25350000
b1111110100 &
1!
#25400000
0!
#25450000
b1111111000 &
1!
#25500000
0!
#25550000
b1111111100 &
1!
#25600000
0!
#25650000
b10000000000 &
1!
#25700000
0!
#25750000
b10000000100 &
1!
#25800000
0!
#25850000
b10000001000 &
1!
#25900000
0!
#25950000
b10000001100 &
1!
#26000000
0!
#26050000
b10000010000 &
1!
#26100000
0!
#26150000
b10000010100 &
1!
#26200000
0!
#26250000
b10000011000 &
1!
#26300000
0!
#26350000
b10000011100 &
1!
#26400000
0!
#26450000
b10000100000 &
1!
#26500000
0!
#26550000
b10000100100 &
1!
#26600000
0!
#26650000
b10000101000 &
1!
#26700000
0!
#26750000
b10000101100 &
1!
#26800000
0!
#26850000
b10000110000 &
1!
#26900000
0!
#26950000
b10000110100 &
1!
#27000000
0!
#27050000
b10000111000 &
1!
#27100000
0!
#27150000
b10000111100 &
1!
#27200000
0!
#27250000
b10001000000 &
1!
#27300000
0!
#27350000
b10001000100 &
1!
#27400000
0!
#27450000
b10001001000 &
1!
#27500000
0!
#27550000
b10001001100 &
1!
#27600000
0!
#27650000
b10001010000 &
1!
#27700000
0!
#27750000
b10001010100 &
1!
#27800000
0!
#27850000
b10001011000 &
1!
#27900000
0!
#27950000
b10001011100 &
1!
#28000000
0!
#28050000
b10001100000 &
1!
#28100000
0!
#28150000
b10001100100 &
1!
#28200000
0!
#28250000
b10001101000 &
1!
#28300000
0!
#28350000
b10001101100 &
1!
#28400000
0!
#28450000
b10001110000 &
1!
#28500000
0!
#28550000
b10001110100 &
1!
#28600000
0!
#28650000
b10001111000 &
1!
#28700000
0!
#28750000
b10001111100 &
1!
#28800000
0!
#28850000
b10010000000 &
1!
#28900000
0!
#28950000
b10010000100 &
1!
#29000000
0!
#29050000
b10010001000 &
1!
#29100000
0!
#29150000
b10010001100 &
1!
#29200000
0!
#29250000
b10010010000 &
1!
#29300000
0!
#29350000
b10010010100 &
1!
#29400000
0!
#29450000
b10010011000 &
1!
#29500000
0!
#29550000
b10010011100 &
1!
#29600000
0!
#29650000
b10010100000 &
1!
#29700000
0!
#29750000
b10010100100 &
1!
#29800000
0!
#29850000
b10010101000 &
1!
#29900000
0!
#29950000
b10010101100 &
1!
#30000000
0!
#30050000
b10010110000 &
1!
#30100000
0!
#30150000
b10010110100 &
1!
#30200000
0!
#30250000
b10010111000 &
1!
#30300000
0!
#30350000
b10010111100 &
1!
#30400000
0!
#30450000
b10011000000 &
1!
#30500000
0!
#30550000
b10011000100 &
1!
#30600000
0!
#30650000
b10011001000 &
1!
#30700000
0!
#30750000
b10011001100 &
1!
#30800000
0!
#30850000
b10011010000 &
1!
#30900000
0!
#30950000
b10011010100 &
1!
#31000000
0!
#31050000
b10011011000 &
1!
#31100000
0!
#31150000
b10011011100 &
1!
#31200000
0!
#31250000
b10011100000 &
1!
#31300000
0!
#31350000
b10011100100 &
1!
#31400000
0!
#31450000
b10011101000 &
1!
#31500000
0!
#31550000
b10011101100 &
1!
#31600000
0!
#31650000
b10011110000 &
1!
#31700000
0!
#31750000
b10011110100 &
1!
#31800000
0!
#31850000
b10011111000 &
1!
#31900000
0!
#31950000
b10011111100 &
1!
#32000000
0!
#32050000
b10100000000 &
1!
#32100000
0!
#32150000
b10100000100 &
1!
#32200000
0!
#32250000
b10100001000 &
1!
#32300000
0!
#32350000
b10100001100 &
1!
#32400000
0!
#32450000
b10100010000 &
1!
#32500000
0!
#32550000
b10100010100 &
1!
#32600000
0!
#32650000
b10100011000 &
1!
#32700000
0!
#32750000
b10100011100 &
1!
#32800000
0!
#32850000
b10100100000 &
1!
#32900000
0!
#32950000
b10100100100 &
1!
#33000000
0!
#33050000
b10100101000 &
1!
#33100000
0!
#33150000
b10100101100 &
1!
#33200000
0!
#33250000
b10100110000 &
1!
#33300000
0!
#33350000
b10100110100 &
1!
#33400000
0!
#33450000
b10100111000 &
1!
#33500000
0!
#33550000
b10100111100 &
1!
#33600000
0!
#33650000
b10101000000 &
1!
#33700000
0!
#33750000
b10101000100 &
1!
#33800000
0!
#33850000
b10101001000 &
1!
#33900000
0!
#33950000
b10101001100 &
1!
#34000000
0!
#34050000
b10101010000 &
1!
#34100000
0!
#34150000
b10101010100 &
1!
#34200000
0!
#34250000
b10101011000 &
1!
#34300000
0!
#34350000
b10101011100 &
1!
#34400000
0!
#34450000
b10101100000 &
1!
#34500000
0!
#34550000
b10101100100 &
1!
#34600000
0!
#34650000
b10101101000 &
1!
#34700000
0!
#34750000
b10101101100 &
1!
#34800000
0!
#34850000
b10101110000 &
1!
#34900000
0!
#34950000
b10101110100 &
1!
#35000000
0!
#35050000
b10101111000 &
1!
#35100000
0!
#35150000
b10101111100 &
1!
#35200000
0!
#35250000
b10110000000 &
1!
#35300000
0!
#35350000
b10110000100 &
1!
#35400000
0!
#35450000
b10110001000 &
1!
#35500000
0!
#35550000
b10110001100 &
1!
#35600000
0!
#35650000
b10110010000 &
1!
#35700000
0!
#35750000
b10110010100 &
1!
#35800000
0!
#35850000
b10110011000 &
1!
#35900000
0!
#35950000
b10110011100 &
1!
#36000000
0!
#36050000
b10110100000 &
1!
#36100000
0!
#36150000
b10110100100 &
1!
#36200000
0!
#36250000
b10110101000 &
1!
#36300000
0!
#36350000
b10110101100 &
1!
#36400000
0!
#36450000
b10110110000 &
1!
#36500000
0!
#36550000
b10110110100 &
1!
#36600000
0!
#36650000
b10110111000 &
1!
#36700000
0!
#36750000
b10110111100 &
1!
#36800000
0!
#36850000
b10111000000 &
1!
#36900000
0!
#36950000
b10111000100 &
1!
#37000000
0!
#37050000
b10111001000 &
1!
#37100000
0!
#37150000
b10111001100 &
1!
#37200000
0!
#37250000
b10111010000 &
1!
#37300000
0!
#37350000
b10111010100 &
1!
#37400000
0!
#37450000
b10111011000 &
1!
#37500000
0!
#37550000
b10111011100 &
1!
#37600000
0!
#37650000
b10111100000 &
1!
#37700000
0!
#37750000
b10111100100 &
1!
#37800000
0!
#37850000
b10111101000 &
1!
#37900000
0!
#37950000
b10111101100 &
1!
#38000000
0!
#38050000
b10111110000 &
1!
#38100000
0!
#38150000
b10111110100 &
1!
#38200000
0!
#38250000
b10111111000 &
1!
#38300000
0!
#38350000
b10111111100 &
1!
#38400000
0!
#38450000
b11000000000 &
1!
#38500000
0!
#38550000
b11000000100 &
1!
#38600000
0!
#38650000
b11000001000 &
1!
#38700000
0!
#38750000
b11000001100 &
1!
#38800000
0!
#38850000
b11000010000 &
1!
#38900000
0!
#38950000
b11000010100 &
1!
#39000000
0!
#39050000
b11000011000 &
1!
#39100000
0!
#39150000
b11000011100 &
1!
#39200000
0!
#39250000
b11000100000 &
1!
#39300000
0!
#39350000
b11000100100 &
1!
#39400000
0!
#39450000
b11000101000 &
1!
#39500000
0!
#39550000
b11000101100 &
1!
#39600000
0!
#39650000
b11000110000 &
1!
#39700000
0!
#39750000
b11000110100 &
1!
#39800000
0!
#39850000
b11000111000 &
1!
#39900000
0!
#39950000
b11000111100 &
1!
#40000000
0!
#40050000
b11001000000 &
1!
#40100000
0!
#40150000
b11001000100 &
1!
#40200000
0!
#40250000
b11001001000 &
1!
#40300000
0!
#40350000
b11001001100 &
1!
#40400000
0!
#40450000
b11001010000 &
1!
#40500000
0!
#40550000
b11001010100 &
1!
#40600000
0!
#40650000
b11001011000 &
1!
#40700000
0!
#40750000
b11001011100 &
1!
#40800000
0!
#40850000
b11001100000 &
1!
#40900000
0!
#40950000
b11001100100 &
1!
#41000000
0!
#41050000
b11001101000 &
1!
#41100000
0!
#41150000
b11001101100 &
1!
#41200000
0!
#41250000
b11001110000 &
1!
#41300000
0!
#41350000
b11001110100 &
1!
#41400000
0!
#41450000
b11001111000 &
1!
#41500000
0!
#41550000
b11001111100 &
1!
#41600000
0!
#41650000
b11010000000 &
1!
#41700000
0!
#41750000
b11010000100 &
1!
#41800000
0!
#41850000
b11010001000 &
1!
#41900000
0!
#41950000
b11010001100 &
1!
#42000000
0!
#42050000
b11010010000 &
1!
#42100000
0!
#42150000
b11010010100 &
1!
#42200000
0!
#42250000
b11010011000 &
1!
#42300000
0!
#42350000
b11010011100 &
1!
#42400000
0!
#42450000
b11010100000 &
1!
#42500000
0!
#42550000
b11010100100 &
1!
#42600000
0!
#42650000
b11010101000 &
1!
#42700000
0!
#42750000
b11010101100 &
1!
#42800000
0!
#42850000
b11010110000 &
1!
#42900000
0!
#42950000
b11010110100 &
1!
#43000000
0!
#43050000
b11010111000 &
1!
#43100000
0!
#43150000
b11010111100 &
1!
#43200000
0!
#43250000
b11011000000 &
1!
#43300000
0!
#43350000
b11011000100 &
1!
#43400000
0!
#43450000
b11011001000 &
1!
#43500000
0!
#43550000
b11011001100 &
1!
#43600000
0!
#43650000
b11011010000 &
1!
#43700000
0!
#43750000
b11011010100 &
1!
#43800000
0!
#43850000
b11011011000 &
1!
#43900000
0!
#43950000
b11011011100 &
1!
#44000000
0!
#44050000
b11011100000 &
1!
#44100000
0!
#44150000
b11011100100 &
1!
#44200000
0!
#44250000
b11011101000 &
1!
#44300000
0!
#44350000
b11011101100 &
1!
#44400000
0!
#44450000
b11011110000 &
1!
#44500000
0!
#44550000
b11011110100 &
1!
#44600000
0!
#44650000
b11011111000 &
1!
#44700000
0!
#44750000
b11011111100 &
1!
#44800000
0!
#44850000
b11100000000 &
1!
#44900000
0!
#44950000
b11100000100 &
1!
#45000000
0!
#45050000
b11100001000 &
1!
#45100000
0!
#45150000
b11100001100 &
1!
#45200000
0!
#45250000
b11100010000 &
1!
#45300000
0!
#45350000
b11100010100 &
1!
#45400000
0!
#45450000
b11100011000 &
1!
#45500000
0!
#45550000
b11100011100 &
1!
#45600000
0!
#45650000
b11100100000 &
1!
#45700000
0!
#45750000
b11100100100 &
1!
#45800000
0!
#45850000
b11100101000 &
1!
#45900000
0!
#45950000
b11100101100 &
1!
#46000000
0!
#46050000
b11100110000 &
1!
#46100000
0!
#46150000
b11100110100 &
1!
#46200000
0!
#46250000
b11100111000 &
1!
#46300000
0!
#46350000
b11100111100 &
1!
#46400000
0!
#46450000
b11101000000 &
1!
#46500000
0!
#46550000
b11101000100 &
1!
#46600000
0!
#46650000
b11101001000 &
1!
#46700000
0!
#46750000
b11101001100 &
1!
#46800000
0!
#46850000
b11101010000 &
1!
#46900000
0!
#46950000
b11101010100 &
1!
#47000000
0!
#47050000
b11101011000 &
1!
#47100000
0!
#47150000
b11101011100 &
1!
#47200000
0!
#47250000
b11101100000 &
1!
#47300000
0!
#47350000
b11101100100 &
1!
#47400000
0!
#47450000
b11101101000 &
1!
#47500000
0!
#47550000
b11101101100 &
1!
#47600000
0!
#47650000
b11101110000 &
1!
#47700000
0!
#47750000
b11101110100 &
1!
#47800000
0!
#47850000
b11101111000 &
1!
#47900000
0!
#47950000
b11101111100 &
1!
#48000000
0!
#48050000
b11110000000 &
1!
#48100000
0!
#48150000
b11110000100 &
1!
#48200000
0!
#48250000
b11110001000 &
1!
#48300000
0!
#48350000
b11110001100 &
1!
#48400000
0!
#48450000
b11110010000 &
1!
#48500000
0!
#48550000
b11110010100 &
1!
#48600000
0!
#48650000
b11110011000 &
1!
#48700000
0!
#48750000
b11110011100 &
1!
#48800000
0!
#48850000
b11110100000 &
1!
#48900000
0!
#48950000
b11110100100 &
1!
#49000000
0!
#49050000
b11110101000 &
1!
#49100000
0!
#49150000
b11110101100 &
1!
#49200000
0!
#49250000
b11110110000 &
1!
#49300000
0!
#49350000
b11110110100 &
1!
#49400000
0!
#49450000
b11110111000 &
1!
#49500000
0!
#49550000
b11110111100 &
1!
#49600000
0!
#49650000
b11111000000 &
1!
#49700000
0!
#49750000
b11111000100 &
1!
#49800000
0!
#49850000
b11111001000 &
1!
#49900000
0!
#49950000
b11111001100 &
1!
#50000000
0!
#50050000
b11111010000 &
1!
#50100000
0!
#50150000
b11111010100 &
1!
#50200000
0!
#50250000
b11111011000 &
1!
#50300000
0!
#50350000
b11111011100 &
1!
#50400000
0!
#50450000
b11111100000 &
1!
#50500000
0!
#50550000
b11111100100 &
1!
#50600000
0!
#50650000
b11111101000 &
1!
#50700000
0!
#50750000
b11111101100 &
1!
#50800000
0!
#50850000
b11111110000 &
1!
#50900000
0!
#50950000
b11111110100 &
1!
#51000000
0!
#51050000
b11111111000 &
1!
#51100000
0!
#51150000
b11111111100 &
1!
#51200000
0!
#51250000
b100000000000 &
1!
#51300000
0!
#51350000
b100000000100 &
1!
#51400000
0!
#51450000
b100000001000 &
1!
#51500000
0!
#51550000
b100000001100 &
1!
#51600000
0!
#51650000
b100000010000 &
1!
#51700000
0!
#51750000
b100000010100 &
1!
#51800000
0!
#51850000
b100000011000 &
1!
#51900000
0!
#51950000
b100000011100 &
1!
#52000000
0!
#52050000
b100000100000 &
1!
#52100000
0!
#52150000
b100000100100 &
1!
#52200000
0!
#52250000
b100000101000 &
1!
#52300000
0!
#52350000
b100000101100 &
1!
#52400000
0!
#52450000
b100000110000 &
1!
#52500000
0!
#52550000
b100000110100 &
1!
#52600000
0!
#52650000
b100000111000 &
1!
#52700000
0!
#52750000
b100000111100 &
1!
#52800000
0!
#52850000
b100001000000 &
1!
#52900000
0!
#52950000
b100001000100 &
1!
#53000000
0!
#53050000
b100001001000 &
1!
#53100000
0!
#53150000
b100001001100 &
1!
#53200000
0!
#53250000
b100001010000 &
1!
#53300000
0!
#53350000
b100001010100 &
1!
#53400000
0!
#53450000
b100001011000 &
1!
#53500000
0!
#53550000
b100001011100 &
1!
#53600000
0!
#53650000
b100001100000 &
1!
#53700000
0!
#53750000
b100001100100 &
1!
#53800000
0!
#53850000
b100001101000 &
1!
#53900000
0!
#53950000
b100001101100 &
1!
#54000000
0!
#54050000
b100001110000 &
1!
#54100000
0!
#54150000
b100001110100 &
1!
#54200000
0!
#54250000
b100001111000 &
1!
#54300000
0!
#54350000
b100001111100 &
1!
#54400000
0!
#54450000
b100010000000 &
1!
#54500000
0!
#54550000
b100010000100 &
1!
#54600000
0!
#54650000
b100010001000 &
1!
#54700000
0!
#54750000
b100010001100 &
1!
#54800000
0!
#54850000
b100010010000 &
1!
#54900000
0!
#54950000
b100010010100 &
1!
#55000000
0!
#55050000
b100010011000 &
1!
#55100000
0!
#55150000
b100010011100 &
1!
#55200000
0!
#55250000
b100010100000 &
1!
#55300000
0!
#55350000
b100010100100 &
1!
#55400000
0!
#55450000
b100010101000 &
1!
#55500000
0!
#55550000
b100010101100 &
1!
#55600000
0!
#55650000
b100010110000 &
1!
#55700000
0!
#55750000
b100010110100 &
1!
#55800000
0!
#55850000
b100010111000 &
1!
#55900000
0!
#55950000
b100010111100 &
1!
#56000000
0!
#56050000
b100011000000 &
1!
#56100000
0!
#56150000
b100011000100 &
1!
#56200000
0!
#56250000
b100011001000 &
1!
#56300000
0!
#56350000
b100011001100 &
1!
#56400000
0!
#56450000
b100011010000 &
1!
#56500000
0!
#56550000
b100011010100 &
1!
#56600000
0!
#56650000
b100011011000 &
1!
#56700000
0!
#56750000
b100011011100 &
1!
#56800000
0!
#56850000
b100011100000 &
1!
#56900000
0!
#56950000
b100011100100 &
1!
#57000000
0!
#57050000
b100011101000 &
1!
#57100000
0!
#57150000
b100011101100 &
1!
#57200000
0!
#57250000
b100011110000 &
1!
#57300000
0!
#57350000
b100011110100 &
1!
#57400000
0!
#57450000
b100011111000 &
1!
#57500000
0!
#57550000
b100011111100 &
1!
#57600000
0!
#57650000
b100100000000 &
1!
#57700000
0!
#57750000
b100100000100 &
1!
#57800000
0!
#57850000
b100100001000 &
1!
#57900000
0!
#57950000
b100100001100 &
1!
#58000000
0!
#58050000
b100100010000 &
1!
#58100000
0!
#58150000
b100100010100 &
1!
#58200000
0!
#58250000
b100100011000 &
1!
#58300000
0!
#58350000
b100100011100 &
1!
#58400000
0!
#58450000
b100100100000 &
1!
#58500000
0!
#58550000
b100100100100 &
1!
#58600000
0!
#58650000
b100100101000 &
1!
#58700000
0!
#58750000
b100100101100 &
1!
#58800000
0!
